fithic/__init__.py
fithic/__main__.py
fithic/fithic-runner.py
fithic/fithic.py
fithic/myStats.py
fithic/myUtils.py
fithic-2.0.1.dist-info/METADATA
fithic-2.0.1.dist-info/RECORD
fithic-2.0.1.dist-info/WHEEL
fithic-2.0.1.dist-info/entry_points.txt
fithic-2.0.1.dist-info/top_level.txt
