Metadata-Version: 2.1
Name: fithic
Version: 2.0.1
Summary: Hi-C Analysis software created and maintained by the Ay Lab
Home-page: http://github.com/ay-lab/fithic/tree/development
Author: Ferhat Ay
Author-email: ferhatay@lji.org
License: MIT
Platform: UNKNOWN
Classifier: Programming Language :: Python :: 3
Classifier: License :: OSI Approved :: MIT License
Classifier: Operating System :: OS Independent
Requires-Python: ~=3.6
Requires-Dist: numpy
Requires-Dist: matplotlib
Requires-Dist: scipy
Requires-Dist: scikit-learn
Requires-Dist: sortedcontainers
